[
    {
        "name": "Abs",
        "attrs": []
    },
    {
        "name": "AbsCriterion",
        "attrs": [
            "sizeAverage"
        ]
    },
    {
        "name": "Add",
        "attrs": [
            "inputSize",
            "scalar"
        ]
    },
    {
        "name": "AddConstant",
        "attrs": [
            "constant_scalar",
            "ip"
        ]
    },
    {
        "name": "BCECriterion",
        "attrs": [
            "weights",
            "sizeAverage"
        ]
    },
    {
        "name": "BatchNormalization",
        "attrs": [
            "nOutput",
            "eps",
            "momentum",
            "affine"
        ]
    },
    {
        "name": "Bilinear",
        "attrs": [
            "inputSize1",
            "inputSize2",
            "outputSize",
            "bias"
        ]
    },
    {
        "name": "CAddTable",
        "attrs": [
            "ip"
        ]
    },
    {
        "name": "CDivTable",
        "attrs": []
    },
    {
        "name": "CMul",
        "attrs": [
            "params"
        ]
    },
    {
        "name": "CMulTable",
        "attrs": []
    },
    {
        "name": "CSubTable",
        "attrs": []
    },
    {
        "name": "Clamp",
        "attrs": [
            "min_value",
            "max_value"
        ]
    },
    {
        "name": "ClassNLLCriterion",
        "attrs": [
            "weights",
            "sizeAverage"
        ]
    },
    {
        "name": "ClassSimplexCriterion",
        "attrs": [
            "nClasses"
        ]
    },
    {
        "name": "Concat",
        "attrs": [
            "dimension"
        ]
    },
    {
        "name": "ConcatTable",
        "attrs": []
    },
    {
        "name": "Contiguous",
        "attrs": []
    },
    {
        "name": "Copy",
        "attrs": [
            "intype",
            "outtype",
            "forceCopy",
            "dontCast"
        ]
    },
    {
        "name": "Cosine",
        "attrs": [
            "inputSize",
            "outputSize"
        ]
    },
    {
        "name": "CosineDistance",
        "attrs": []
    },
    {
        "name": "CosineEmbeddingCriterion",
        "attrs": [
            "margin"
        ]
    },
    {
        "name": "CriterionTable",
        "attrs": [
            "criterion"
        ]
    },
    {
        "name": "CrossEntropyCriterion",
        "attrs": [
            "weights"
        ]
    },
    {
        "name": "DepthConcat",
        "attrs": [
            "dimension"
        ]
    },
    {
        "name": "DistKLDivCriterion",
        "attrs": []
    },
    {
        "name": "DotProduct",
        "attrs": []
    },
    {
        "name": "Dropout",
        "attrs": [
            "p",
            "v1",
            "inplace"
        ]
    },
    {
        "name": "ELU",
        "attrs": [
            "alpha",
            "inplace"
        ]
    },
    {
        "name": "Euclidean",
        "attrs": [
            "inputSize",
            "outputSize"
        ]
    },
    {
        "name": "Exp",
        "attrs": []
    },
    {
        "name": "FlattenTable",
        "attrs": []
    },
    {
        "name": "GradientReversal",
        "attrs": []
    },
    {
        "name": "HardShrink",
        "attrs": [
            "lam"
        ]
    },
    {
        "name": "HardTanh",
        "attrs": [
            "min_value",
            "max_value"
        ]
    },
    {
        "name": "HingeEmbeddingCriterion",
        "attrs": [
            "margin"
        ]
    },
    {
        "name": "Identity",
        "attrs": []
    },
    {
        "name": "Index",
        "attrs": [
            "dimension"
        ]
    },
    {
        "name": "JoinTable",
        "attrs": [
            "dimension",
            "nInputDims"
        ]
    },
    {
        "name": "L1Cost",
        "attrs": []
    },
    {
        "name": "L1HingeEmbeddingCriterion",
        "attrs": [
            "margin"
        ]
    },
    {
        "name": "L1Penalty",
        "attrs": [
            "l1weight",
            "sizeAverage",
            "provideOutput"
        ]
    },
    {
        "name": "LeakyReLU",
        "attrs": [
            "negval",
            "ip"
        ]
    },
    {
        "name": "Linear",
        "attrs": [
            "inputSize",
            "outputSize",
            "bias"
        ]
    },
    {
        "name": "Log",
        "attrs": [
            "inputSize"
        ]
    },
    {
        "name": "LogSigmoid",
        "attrs": []
    },
    {
        "name": "LogSoftMax",
        "attrs": []
    },
    {
        "name": "LookupTable",
        "attrs": [
            "nIndex",
            "nOutput",
            "paddingValue",
            "maxNorm",
            "normType",
            "paddingValue",
            "maxNorm",
            "normType",
            "shouldScaleGradByFreq"
        ]
    },
    {
        "name": "MM",
        "attrs": [
            "transA",
            "transB"
        ]
    },
    {
        "name": "MSECriterion",
        "attrs": [
            "sizeAverage"
        ]
    },
    {
        "name": "MV",
        "attrs": [
            "trans"
        ]
    },
    {
        "name": "MarginCriterion",
        "attrs": [
            "margin"
        ]
    },
    {
        "name": "MarginRankingCriterion",
        "attrs": [
            "margin"
        ]
    },
    {
        "name": "MaskedSelect",
        "attrs": []
    },
    {
        "name": "Max",
        "attrs": [
            "dimension",
            "nInputDims"
        ]
    },
    {
        "name": "Mean",
        "attrs": [
            "dimension",
            "nInputDims"
        ]
    },
    {
        "name": "Min",
        "attrs": [
            "dimension",
            "nInputDims"
        ]
    },
    {
        "name": "MixtureTable",
        "attrs": [
            "dim"
        ]
    },
    {
        "name": "Mul",
        "attrs": []
    },
    {
        "name": "MulConstant",
        "attrs": [
            "constant_scalar",
            "ip"
        ]
    },
    {
        "name": "MultiCriterion",
        "attrs": []
    },
    {
        "name": "MultiLabelMarginCriterion",
        "attrs": []
    },
    {
        "name": "MultiLabelSoftMarginCriterion",
        "attrs": [
            "weights"
        ]
    },
    {
        "name": "MultiMarginCriterion",
        "attrs": [
            "p",
            "weights",
            "margin"
        ]
    },
    {
        "name": "Narrow",
        "attrs": [
            "dimension",
            "offset",
            "length"
        ]
    },
    {
        "name": "NarrowTable",
        "attrs": [
            "offset",
            "length"
        ]
    },
    {
        "name": "Normalize",
        "attrs": [
            "p",
            "eps"
        ]
    },
    {
        "name": "PReLU",
        "attrs": [
            "nOutputPlane"
        ]
    },
    {
        "name": "Padding",
        "attrs": [
            "dim",
            "pad",
            "nInputDim",
            "value",
            "index"
        ]
    },
    {
        "name": "PairwiseDistance",
        "attrs": [
            "p"
        ]
    },
    {
        "name": "Parallel",
        "attrs": [
            "inputDimension",
            "outputDimension"
        ]
    },
    {
        "name": "ParallelCriterion",
        "attrs": [
            "repeatTarget"
        ]
    },
    {
        "name": "ParallelTable",
        "attrs": []
    },
    {
        "name": "PartialLinear",
        "attrs": [
            "inputsize",
            "outputsize",
            "bias"
        ]
    },
    {
        "name": "Power",
        "attrs": [
            "p"
        ]
    },
    {
        "name": "RReLU",
        "attrs": [
            "l",
            "u",
            "ip"
        ]
    },
    {
        "name": "ReLU",
        "attrs": [
            "p"
        ]
    },
    {
        "name": "Replicate",
        "attrs": [
            "nf",
            "dim",
            "ndim"
        ]
    },
    {
        "name": "Reshape",
        "attrs": [
            "params"
        ]
    },
    {
        "name": "Select",
        "attrs": [
            "dimension",
            "index"
        ]
    },
    {
        "name": "SelectTable",
        "attrs": [
            "index"
        ]
    },
    {
        "name": "Sigmoid",
        "attrs": []
    },
    {
        "name": "SmoothL1Criterion",
        "attrs": [
            "sizeAverage"
        ]
    },
    {
        "name": "SoftMarginCriterion",
        "attrs": []
    },
    {
        "name": "SoftMax",
        "attrs": []
    },
    {
        "name": "SoftMin",
        "attrs": []
    },
    {
        "name": "SoftPlus",
        "attrs": [
            "beta"
        ]
    },
    {
        "name": "SoftShrink",
        "attrs": [
            "lam"
        ]
    },
    {
        "name": "SoftSign",
        "attrs": []
    },
    {
        "name": "SparseLinear",
        "attrs": [
            "inputSize",
            "outputSize",
            "doGradInput"
        ]
    },
    {
        "name": "SpatialAdaptiveMaxPooling",
        "attrs": [
            "W",
            "H"
        ]
    },
    {
        "name": "SpatialAveragePooling",
        "attrs": [
            "kW",
            "kH",
            "dW",
            "dH",
            "padW",
            "padH",
            "ceil_mode",
            "count_include_pad"
        ]
    },
    {
        "name": "SpatialBatchNormalization",
        "attrs": [
            "nOutput",
            "eps",
            "momentum",
            "affine"
        ]
    },
    {
        "name": "SpatialContrastiveNormalization",
        "attrs": [
            "nInputPlane",
            "kernel",
            "threshold",
            "thresval"
        ]
    },
    {
        "name": "SpatialConvolution",
        "attrs": [
            "nInputPlane",
            "nOutputPlane",
            "kW",
            "kH",
            "dW",
            "dH",
            "padW",
            "padH"
        ]
    },
    {
        "name": "SpatialConvolutionLocal",
        "attrs": [
            "nInputPlane",
            "nOutputPlane",
            "iW",
            "iH",
            "kW",
            "kH",
            "dW",
            "dH",
            "padW",
            "padH"
        ]
    },
    {
        "name": "SpatialConvolutionMM",
        "attrs": [
            "nInputPlane",
            "nOutputPlane",
            "kW",
            "kH",
            "dW",
            "dH",
            "padW",
            "padH"
        ]
    },
    {
        "name": "SpatialConvolutionMap",
        "attrs": [
            "conMatrix",
            "kW",
            "kH",
            "dW",
            "dH"
        ]
    },
    {
        "name": "SpatialCrossMapLRN",
        "attrs": [
            "size",
            "alpha",
            "beta",
            "k"
        ]
    },
    {
        "name": "SpatialDivisiveNormalization",
        "attrs": [
            "nInputPlane",
            "kernel",
            "threshold",
            "thresval"
        ]
    },
    {
        "name": "SpatialDropout",
        "attrs": [
            "p"
        ]
    },
    {
        "name": "SpatialFractionalMaxPooling",
        "attrs": [
            "poolSizeW",
            "poolSizeH",
            "arg1",
            "arg2"
        ]
    },
    {
        "name": "SpatialFullConvolution",
        "attrs": [
            "nInputPlane",
            "nOutputPlane",
            "kW",
            "kH",
            "dW",
            "dH",
            "padW",
            "padH",
            "adjW",
            "adjH"
        ]
    },
    {
        "name": "SpatialFullConvolutionMap",
        "attrs": [
            "conMatrix",
            "kW",
            "kH",
            "dW",
            "dH"
        ]
    },
    {
        "name": "SpatialLPPooling",
        "attrs": [
            "nInputPlane",
            "pnorm",
            "kW",
            "kH",
            "dW",
            "dH"
        ]
    },
    {
        "name": "SpatialMaxPooling",
        "attrs": [
            "kW",
            "kH",
            "dW",
            "dH",
            "padW",
            "padH",
            "ceil_mode"
        ]
    },
    {
        "name": "SpatialMaxUnpooling",
        "attrs": [
            "poolingModule"
        ]
    },
    {
        "name": "SpatialReflectionPadding",
        "attrs": [
            "pad_l",
            "pad_r",
            "pad_t",
            "pad_b"
        ]
    },
    {
        "name": "SpatialReplicationPadding",
        "attrs": [
            "pad_l",
            "pad_r",
            "pad_t",
            "pad_b"
        ]
    },
    {
        "name": "SpatialSoftMax",
        "attrs": []
    },
    {
        "name": "SpatialSubSampling",
        "attrs": [
            "nInputPlane",
            "kW",
            "kH",
            "dW",
            "dH"
        ]
    },
    {
        "name": "SpatialSubtractiveNormalization",
        "attrs": [
            "nInputPlane",
            "kernel"
        ]
    },
    {
        "name": "SpatialUpSamplingNearest",
        "attrs": [
            "scale"
        ]
    },
    {
        "name": "SpatialZeroPadding",
        "attrs": [
            "pad_l",
            "pad_r",
            "pad_t",
            "pad_b"
        ]
    },
    {
        "name": "SplitTable",
        "attrs": [
            "dimension",
            "nInputDims"
        ]
    },
    {
        "name": "Sqrt",
        "attrs": [
            "b"
        ]
    },
    {
        "name": "Square",
        "attrs": [
            "args"
        ]
    },
    {
        "name": "Squeeze",
        "attrs": [
            "dim",
            "numInputDims",
            "numInputDims"
        ]
    },
    {
        "name": "Sum",
        "attrs": [
            "dimension",
            "nInputDims",
            "sizeAverage"
        ]
    },
    {
        "name": "Tanh",
        "attrs": []
    },
    {
        "name": "TanhShrink",
        "attrs": []
    },
    {
        "name": "TemporalConvolution",
        "attrs": [
            "inputFrameSize",
            "outputFrameSize",
            "kW",
            "dW"
        ]
    },
    {
        "name": "TemporalMaxPooling",
        "attrs": [
            "kW",
            "dW"
        ]
    },
    {
        "name": "TemporalSubSampling",
        "attrs": [
            "inputFrameSize",
            "kW",
            "dW"
        ]
    },
    {
        "name": "Threshold",
        "attrs": [
            "th",
            "v",
            "ip"
        ]
    },
    {
        "name": "Transpose",
        "attrs": [
            "params"
        ]
    },
    {
        "name": "Unsqueeze",
        "attrs": [
            "pos",
            "numInputDims",
            "numInputDims"
        ]
    },
    {
        "name": "View",
        "attrs": [
            "params",
            "numInputDims"
        ]
    },
    {
        "name": "VolumetricAveragePooling",
        "attrs": [
            "kT",
            "kW",
            "kH",
            "dT",
            "dW",
            "dH"
        ]
    },
    {
        "name": "VolumetricBatchNormalization",
        "attrs": [
            "nOutput",
            "eps",
            "momentum",
            "affine"
        ]
    },
    {
        "name": "VolumetricConvolution",
        "attrs": [
            "nInputPlane",
            "nOutputPlane",
            "kT",
            "kW",
            "kH",
            "dT",
            "dW",
            "dH",
            "padT",
            "padW",
            "padH"
        ]
    },
    {
        "name": "VolumetricDropout",
        "attrs": [
            "p"
        ]
    },
    {
        "name": "VolumetricFullConvolution",
        "attrs": [
            "nInputPlane",
            "nOutputPlane",
            "kT",
            "kW",
            "kH",
            "dT",
            "dW",
            "dH",
            "padT",
            "padW",
            "padH",
            "adjT",
            "adjW",
            "adjH"
        ]
    },
    {
        "name": "VolumetricMaxPooling",
        "attrs": [
            "kT",
            "kW",
            "kH",
            "dT",
            "dW",
            "dH",
            "padT",
            "padW",
            "padH",
            "ceil_mode"
        ]
    },
    {
        "name": "VolumetricMaxUnpooling",
        "attrs": [
            "poolingModule"
        ]
    },
    {
        "name": "WeightedEuclidean",
        "attrs": [
            "inputSize",
            "outputSize"
        ]
    },
    {
        "name": "WeightedMSECriterion",
        "attrs": [
            "w"
        ]
    }
]